pygbag_builder/__init__.py
pygbag_builder/__main__.py
pygbag_builder/insert_await.py
pygbag_builder/insert_sleep.py
pygbag_builder/main_flow.py
pygbag_builder/make_dir.py
pygbag_builder/make_repo.py
pygbag_builder/set_page.py
pygbag_builder-0.1.4.dist-info/METADATA
pygbag_builder-0.1.4.dist-info/WHEEL
pygbag_builder-0.1.4.dist-info/entry_points.txt
pygbag_builder-0.1.4.dist-info/top_level.txt
pygbag_builder-0.1.4.dist-info/RECORD
