Metadata-Version: 2.1
Name: pygbag-builder
Version: 0.1.4
Summary: A module to support using pygbag
Home-page: https://github.com/prosamo/pygbag-builder
Author: Prosamo
Author-email: prosamo314@gmail.com
Classifier: Programming Language :: Python :: 3
Classifier: License :: OSI Approved :: MIT License
Classifier: Operating System :: OS Independent
Requires-Python: >=3.6
Requires-Dist: pygame
Requires-Dist: pygbag
Requires-Dist: astor
Requires-Dist: requests
